setup.py
pyconfd/__init__.py
pyconfd/core.py
pyconfd/logstuff.py
pyconfd/plugin.py
pyconfd.egg-info/PKG-INFO
pyconfd.egg-info/SOURCES.txt
pyconfd.egg-info/dependency_links.txt
pyconfd.egg-info/entry_points.txt
pyconfd.egg-info/requires.txt
pyconfd.egg-info/top_level.txt