Metadata-Version: 1.1
Name: pyconfd
Version: 0.0.5
Summary: Auto update config files from consul or etcd.
Home-page: https://github.com/kanzure/pyconfd
Author: Bryan Bishop
Author-email: kanzure@gmail.com
License: BSD
Platform: UNKNOWN
Classifier: Intended Audience :: Developers
Classifier: Natural Language :: English
Classifier: Programming Language :: Python
Classifier: Programming Language :: Python :: 2.7
Classifier: Programming Language :: Python :: 3
Classifier: Programming Language :: Python :: 3.3
